airflow_file_to_bq
