Metadata-Version: 2.1
Name: airflow-file-to-bq
Version: 0.1.7
Summary: Specialized Airflow operators for moving files from a GCS-bucket to Landing-Zone, Staging-Zone and Production-Zone in BigQuery
Home-page: https://github.com/pypa/sampleproject
Author: Florian Pribahsnik
Author-email: florian@pribahsnik.com
License: MIT
Platform: UNKNOWN
Classifier: Programming Language :: Python :: 3
Classifier: License :: OSI Approved :: MIT License
Classifier: Operating System :: OS Independent
License-File: LICENSE
